<?xml version="1.0" encoding="UTF-8"?><?xml-stylesheet type='text/xsl' href='_UpgradeReport_Files/UpgradeReport.xslt'?><UpgradeLog>
<Properties><Property Name="Solution" Value="dcrypt">
</Property><Property Name="Solution File" Value="C:\Git\dcrypt\dcrypt.sln">
</Property><Property Name="Date" Value="Monday, June 04, 2012">
</Property><Property Name="Time" Value="12:50 PM">
</Property></Properties><Event ErrorLevel="0" Project="driver" Source="sys\driver.vcproj" Description="Converting project file 'C:\Git\dcrypt\sys\driver.vcproj'.">
</Event><Event ErrorLevel="1" Project="driver" Source="sys\driver.vcproj" Description="VCWebServiceProxyGeneratorTool is no longer supported. The tool has been removed from your project settings.">
</Event><Event ErrorLevel="1" Project="driver" Source="sys\driver.vcproj" Description="Failed to fully upgrade FileConfiguration for '..\crypto\i386\aes_i386.asm'. Having multiple tools for the same file is unsupported in MSBuild. Tool 'CustomBuildStep' will be replaced by 'MASM'.">
</Event><Event ErrorLevel="1" Project="driver" Source="sys\driver.vcproj" Description="Failed to fully upgrade FileConfiguration for '..\crypto\i386\aes_padlock_i386.asm'. Having multiple tools for the same file is unsupported in MSBuild. Tool 'CustomBuildStep' will be replaced by 'MASM'.">
</Event><Event ErrorLevel="1" Project="driver" Source="sys\driver.vcproj" Description="Failed to fully upgrade FileConfiguration for '..\crypto\i386\twofish_i386.asm'. Having multiple tools for the same file is unsupported in MSBuild. Tool 'CustomBuildStep' will be replaced by 'MASM'.">
</Event><Event ErrorLevel="1" Project="driver" Source="sys\driver.vcproj" Description="Failed to fully upgrade FileConfiguration for '..\crypto\i386\xts_aes_ni_i386.asm'. Having multiple tools for the same file is unsupported in MSBuild. Tool 'CustomBuildStep' will be replaced by 'MASM'.">
</Event><Event ErrorLevel="1" Project="driver" Source="sys\driver.vcproj" Description="Failed to fully upgrade FileConfiguration for '..\crypto\amd64\aes_amd64.asm'. Having multiple tools for the same file is unsupported in MSBuild. Tool 'MASM' will be replaced by 'CustomBuildStep'.">
</Event><Event ErrorLevel="1" Project="driver" Source="sys\driver.vcproj" Description="Failed to fully upgrade FileConfiguration for '..\crypto\amd64\aes_padlock_amd64.asm'. Having multiple tools for the same file is unsupported in MSBuild. Tool 'MASM' will be replaced by 'CustomBuildStep'.">
</Event><Event ErrorLevel="1" Project="driver" Source="sys\driver.vcproj" Description="Failed to fully upgrade FileConfiguration for '..\crypto\amd64\twofish_amd64.asm'. Having multiple tools for the same file is unsupported in MSBuild. Tool 'MASM' will be replaced by 'CustomBuildStep'.">
</Event><Event ErrorLevel="1" Project="driver" Source="sys\driver.vcproj" Description="Failed to fully upgrade FileConfiguration for '..\crypto\amd64\xts_aes_ni_amd64.asm'. Having multiple tools for the same file is unsupported in MSBuild. Tool 'MASM' will be replaced by 'CustomBuildStep'.">
</Event><Event ErrorLevel="1" Project="driver" Source="sys\driver.vcproj" Description="All user macros reported below for configuration 'Release|Win32' are used before their definition, which can cause undesirable build results; this is not supported in this release. You can resolve this by changing the inclusion order of the consuming property sheets and making sure they come after the property sheets defining the user macros.">
</Event><Event ErrorLevel="1" Project="driver" Source="sys\driver.vcproj" Description="MSB4211: C:\Program Files (x86)\MSBuild\Microsoft.Cpp\v4.0\Microsoft.CppCommon.targets (36,5); The property &quot;TargetPath&quot; is being set to a value for the first time, but it was already consumed at &quot;C:\Git\dcrypt\sys\driver.vcxproj&quot;.">
</Event><Event ErrorLevel="1" Project="driver" Source="sys\driver.vcproj" Description="All user macros reported below for configuration 'Release|x64' are used before their definition, which can cause undesirable build results; this is not supported in this release. You can resolve this by changing the inclusion order of the consuming property sheets and making sure they come after the property sheets defining the user macros.">
</Event><Event ErrorLevel="1" Project="driver" Source="sys\driver.vcproj" Description="MSB4211: C:\Program Files (x86)\MSBuild\Microsoft.Cpp\v4.0\Microsoft.CppCommon.targets (36,5); The property &quot;TargetPath&quot; is being set to a value for the first time, but it was already consumed at &quot;C:\Git\dcrypt\sys\driver.vcxproj&quot;.">
</Event><Event ErrorLevel="1" Project="driver" Source="sys\driver.vcproj" Description="VCConvertEngine could not convert attribute CommandLine = yasm -Xvc -f win32 -o &quot;$(OutDir)obj\$(ProjectName)\%(Filename).obj&quot; &quot;%(FullPath)&quot;&#xA; under VCCustomBuildTool Release|Win32.">
</Event><Event ErrorLevel="1" Project="driver" Source="sys\driver.vcproj" Description="VCConvertEngine could not convert attribute Outputs = $(OutDir)obj\$(ProjectName)\%(Filename).obj under VCCustomBuildTool Release|Win32.">
</Event><Event ErrorLevel="1" Project="driver" Source="sys\driver.vcproj" Description="VCConvertEngine could not convert attribute CommandLine = yasm -Xvc -f win32 -o &quot;$(OutDir)obj\$(ProjectName)\%(Filename).obj&quot; &quot;%(FullPath)&quot;&#xA; under VCCustomBuildTool Release|Win32.">
</Event><Event ErrorLevel="1" Project="driver" Source="sys\driver.vcproj" Description="VCConvertEngine could not convert attribute Outputs = $(OutDir)obj\$(ProjectName)\%(Filename).obj under VCCustomBuildTool Release|Win32.">
</Event><Event ErrorLevel="1" Project="driver" Source="sys\driver.vcproj" Description="VCConvertEngine could not convert attribute CommandLine = yasm -Xvc -f win32 -o &quot;$(OutDir)obj\$(ProjectName)\%(Filename).obj&quot; &quot;%(FullPath)&quot;&#xA; under VCCustomBuildTool Release|Win32.">
</Event><Event ErrorLevel="1" Project="driver" Source="sys\driver.vcproj" Description="VCConvertEngine could not convert attribute Outputs = $(OutDir)obj\$(ProjectName)\%(Filename).obj under VCCustomBuildTool Release|Win32.">
</Event><Event ErrorLevel="1" Project="driver" Source="sys\driver.vcproj" Description="VCConvertEngine could not convert attribute CommandLine = yasm -Xvc -f win32 -o &quot;$(OutDir)obj\$(ProjectName)\%(Filename).obj&quot; &quot;%(FullPath)&quot;&#xA; under VCCustomBuildTool Release|Win32.">
</Event><Event ErrorLevel="1" Project="driver" Source="sys\driver.vcproj" Description="VCConvertEngine could not convert attribute Outputs = $(OutDir)obj\$(ProjectName)\%(Filename).obj under VCCustomBuildTool Release|Win32.">
</Event><Event ErrorLevel="1" Project="driver" Source="sys\driver.vcproj" Description="MSB8012: $(TargetName) ('driver') does not match the Linker's OutputFile property value 'C:\Git\dcrypt\\Release\i386\dcrypt.sys' ('dcrypt') in project configuration 'Release|Win32'. This may cause your project to build incorrectly. To correct this, please make sure that $(TargetName) property value matches the value specified in %(Link.OutputFile).">
</Event><Event ErrorLevel="1" Project="driver" Source="sys\driver.vcproj" Description="MSB8012: $(TargetExt) ('.dll') does not match the Linker's OutputFile property value 'C:\Git\dcrypt\\Release\i386\dcrypt.sys' ('.sys') in project configuration 'Release|Win32'. This may cause your project to build incorrectly. To correct this, please make sure that $(TargetExt) property value matches the value specified in %(Link.OutputFile).">
</Event><Event ErrorLevel="1" Project="driver" Source="sys\driver.vcproj" Description="MSB8012: $(TargetPath) ('C:\Git\dcrypt\\Release\i386\driver.dll') does not match the Linker's OutputFile property value 'C:\Git\dcrypt\\Release\i386\dcrypt.sys' ('C:\Git\dcrypt\\Release\i386\dcrypt.sys') in project configuration 'Release|Win32'. This may cause your project to build incorrectly. To correct this, please make sure that $(TargetPath) property value matches the value specified in %(Link.OutputFile).">
</Event><Event ErrorLevel="1" Project="driver" Source="sys\driver.vcproj" Description="MSB8012: $(TargetName) ('driver') does not match the Linker's OutputFile property value 'C:\Git\dcrypt\\Release\amd64\dcrypt.sys' ('dcrypt') in project configuration 'Release|x64'. This may cause your project to build incorrectly. To correct this, please make sure that $(TargetName) property value matches the value specified in %(Link.OutputFile).">
</Event><Event ErrorLevel="1" Project="driver" Source="sys\driver.vcproj" Description="MSB8012: $(TargetExt) ('.dll') does not match the Linker's OutputFile property value 'C:\Git\dcrypt\\Release\amd64\dcrypt.sys' ('.sys') in project configuration 'Release|x64'. This may cause your project to build incorrectly. To correct this, please make sure that $(TargetExt) property value matches the value specified in %(Link.OutputFile).">
</Event><Event ErrorLevel="1" Project="driver" Source="sys\driver.vcproj" Description="MSB8012: $(TargetPath) ('C:\Git\dcrypt\\Release\amd64\driver.dll') does not match the Linker's OutputFile property value 'C:\Git\dcrypt\\Release\amd64\dcrypt.sys' ('C:\Git\dcrypt\\Release\amd64\dcrypt.sys') in project configuration 'Release|x64'. This may cause your project to build incorrectly. To correct this, please make sure that $(TargetPath) property value matches the value specified in %(Link.OutputFile).">
</Event><Event ErrorLevel="0" Project="driver" Source="sys\driver.vcproj" Description="Done converting to new project file 'C:\Git\dcrypt\sys\driver.vcxproj'.">
</Event><Event ErrorLevel="3" Project="driver" Source="sys\driver.vcproj" Description="Converted">
</Event><Event ErrorLevel="0" Project="dcapi" Source="dcapi\dcapi.vcproj" Description="Converting project file 'C:\Git\dcrypt\dcapi\dcapi.vcproj'.">
</Event><Event ErrorLevel="1" Project="dcapi" Source="dcapi\dcapi.vcproj" Description="VCWebServiceProxyGeneratorTool is no longer supported. The tool has been removed from your project settings.">
</Event><Event ErrorLevel="1" Project="dcapi" Source="dcapi\dcapi.vcproj" Description="VCConvertEngine could not convert attribute DependencyInformationFile = $(OutDir)obj\$(ProjectName)\mt.dep under Tool VCManifestTool.">
</Event><Event ErrorLevel="1" Project="dcapi" Source="dcapi\dcapi.vcproj" Description="VCConvertEngine could not convert attribute DependencyInformationFile = $(OutDir)obj\$(ProjectName)\mt.dep under Tool VCManifestTool.">
</Event><Event ErrorLevel="0" Project="dcapi" Source="dcapi\dcapi.vcproj" Description="Done converting to new project file 'C:\Git\dcrypt\dcapi\dcapi.vcxproj'.">
</Event><Event ErrorLevel="3" Project="dcapi" Source="dcapi\dcapi.vcproj" Description="Converted">
</Event><Event ErrorLevel="0" Project="dccon" Source="dccon\dccon.vcproj" Description="Converting project file 'C:\Git\dcrypt\dccon\dccon.vcproj'.">
</Event><Event ErrorLevel="1" Project="dccon" Source="dccon\dccon.vcproj" Description="VCWebServiceProxyGeneratorTool is no longer supported. The tool has been removed from your project settings.">
</Event><Event ErrorLevel="1" Project="dccon" Source="dccon\dccon.vcproj" Description="VCConvertEngine could not convert attribute DependencyInformationFile = $(OutDir)obj\$(ProjectName)\mt.dep under Tool VCManifestTool.">
</Event><Event ErrorLevel="1" Project="dccon" Source="dccon\dccon.vcproj" Description="VCConvertEngine could not convert attribute DependencyInformationFile = $(OutDir)obj\$(ProjectName)\mt.dep under Tool VCManifestTool.">
</Event><Event ErrorLevel="1" Project="dccon" Source="dccon\dccon.vcproj" Description="VCConvertEngine could not convert attribute DependencyInformationFile = $(OutDir)obj\$(ProjectName)\mt.dep under Tool VCManifestTool.">
</Event><Event ErrorLevel="1" Project="dccon" Source="dccon\dccon.vcproj" Description="VCConvertEngine could not convert attribute DependencyInformationFile = $(OutDir)obj\$(ProjectName)\mt.dep under Tool VCManifestTool.">
</Event><Event ErrorLevel="0" Project="dccon" Source="dccon\dccon.vcproj" Description="Done converting to new project file 'C:\Git\dcrypt\dccon\dccon.vcxproj'.">
</Event><Event ErrorLevel="3" Project="dccon" Source="dccon\dccon.vcproj" Description="Converted">
</Event><Event ErrorLevel="0" Project="gui" Source="gui\gui.vcproj" Description="Converting project file 'C:\Git\dcrypt\gui\gui.vcproj'.">
</Event><Event ErrorLevel="1" Project="gui" Source="gui\gui.vcproj" Description="VCWebServiceProxyGeneratorTool is no longer supported. The tool has been removed from your project settings.">
</Event><Event ErrorLevel="1" Project="gui" Source="gui\gui.vcproj" Description="VCConvertEngine could not convert attribute DependencyInformationFile = $(OutDir)obj\$(ProjectName)\mt.dep under Tool VCManifestTool.">
</Event><Event ErrorLevel="1" Project="gui" Source="gui\gui.vcproj" Description="VCConvertEngine could not convert attribute DependencyInformationFile = $(OutDir)obj\$(ProjectName)\mt.dep under Tool VCManifestTool.">
</Event><Event ErrorLevel="1" Project="gui" Source="gui\gui.vcproj" Description="VCConvertEngine could not convert attribute DependencyInformationFile = $(OutDir)obj\$(ProjectName)\mt.dep under Tool VCManifestTool.">
</Event><Event ErrorLevel="1" Project="gui" Source="gui\gui.vcproj" Description="VCConvertEngine could not convert attribute DependencyInformationFile = $(OutDir)obj\$(ProjectName)\mt.dep under Tool VCManifestTool.">
</Event><Event ErrorLevel="0" Project="gui" Source="gui\gui.vcproj" Description="Done converting to new project file 'C:\Git\dcrypt\gui\gui.vcxproj'.">
</Event><Event ErrorLevel="3" Project="gui" Source="gui\gui.vcproj" Description="Converted">
</Event><Event ErrorLevel="0" Project="dc_fsf" Source="dc_fsf\dc_fsf.vcproj" Description="Converting project file 'C:\Git\dcrypt\dc_fsf\dc_fsf.vcproj'.">
</Event><Event ErrorLevel="1" Project="dc_fsf" Source="dc_fsf\dc_fsf.vcproj" Description="VCWebServiceProxyGeneratorTool is no longer supported. The tool has been removed from your project settings.">
</Event><Event ErrorLevel="1" Project="dc_fsf" Source="dc_fsf\dc_fsf.vcproj" Description="All user macros reported below for configuration 'Release|Win32' are used before their definition, which can cause undesirable build results; this is not supported in this release. You can resolve this by changing the inclusion order of the consuming property sheets and making sure they come after the property sheets defining the user macros.">
</Event><Event ErrorLevel="1" Project="dc_fsf" Source="dc_fsf\dc_fsf.vcproj" Description="MSB4211: C:\Program Files (x86)\MSBuild\Microsoft.Cpp\v4.0\Microsoft.CppCommon.targets (36,5); The property &quot;TargetPath&quot; is being set to a value for the first time, but it was already consumed at &quot;C:\Git\dcrypt\dc_fsf\dc_fsf.vcxproj&quot;.">
</Event><Event ErrorLevel="1" Project="dc_fsf" Source="dc_fsf\dc_fsf.vcproj" Description="All user macros reported below for configuration 'Release|x64' are used before their definition, which can cause undesirable build results; this is not supported in this release. You can resolve this by changing the inclusion order of the consuming property sheets and making sure they come after the property sheets defining the user macros.">
</Event><Event ErrorLevel="1" Project="dc_fsf" Source="dc_fsf\dc_fsf.vcproj" Description="MSB4211: C:\Program Files (x86)\MSBuild\Microsoft.Cpp\v4.0\Microsoft.CppCommon.targets (36,5); The property &quot;TargetPath&quot; is being set to a value for the first time, but it was already consumed at &quot;C:\Git\dcrypt\dc_fsf\dc_fsf.vcxproj&quot;.">
</Event><Event ErrorLevel="1" Project="dc_fsf" Source="dc_fsf\dc_fsf.vcproj" Description="MSB8012: $(TargetExt) ('.dll') does not match the Linker's OutputFile property value 'C:\Git\dcrypt\\Release\i386\dc_fsf.sys' ('.sys') in project configuration 'Release|Win32'. This may cause your project to build incorrectly. To correct this, please make sure that $(TargetExt) property value matches the value specified in %(Link.OutputFile).">
</Event><Event ErrorLevel="1" Project="dc_fsf" Source="dc_fsf\dc_fsf.vcproj" Description="MSB8012: $(TargetPath) ('C:\Git\dcrypt\\Release\i386\dc_fsf.dll') does not match the Linker's OutputFile property value 'C:\Git\dcrypt\\Release\i386\dc_fsf.sys' ('C:\Git\dcrypt\\Release\i386\dc_fsf.sys') in project configuration 'Release|Win32'. This may cause your project to build incorrectly. To correct this, please make sure that $(TargetPath) property value matches the value specified in %(Link.OutputFile).">
</Event><Event ErrorLevel="1" Project="dc_fsf" Source="dc_fsf\dc_fsf.vcproj" Description="MSB8012: $(TargetExt) ('.dll') does not match the Linker's OutputFile property value 'C:\Git\dcrypt\\Release\amd64\dc_fsf.sys' ('.sys') in project configuration 'Release|x64'. This may cause your project to build incorrectly. To correct this, please make sure that $(TargetExt) property value matches the value specified in %(Link.OutputFile).">
</Event><Event ErrorLevel="1" Project="dc_fsf" Source="dc_fsf\dc_fsf.vcproj" Description="MSB8012: $(TargetPath) ('C:\Git\dcrypt\\Release\amd64\dc_fsf.dll') does not match the Linker's OutputFile property value 'C:\Git\dcrypt\\Release\amd64\dc_fsf.sys' ('C:\Git\dcrypt\\Release\amd64\dc_fsf.sys') in project configuration 'Release|x64'. This may cause your project to build incorrectly. To correct this, please make sure that $(TargetPath) property value matches the value specified in %(Link.OutputFile).">
</Event><Event ErrorLevel="0" Project="dc_fsf" Source="dc_fsf\dc_fsf.vcproj" Description="Done converting to new project file 'C:\Git\dcrypt\dc_fsf\dc_fsf.vcxproj'.">
</Event><Event ErrorLevel="3" Project="dc_fsf" Source="dc_fsf\dc_fsf.vcproj" Description="Converted">
</Event><Event ErrorLevel="0" Project="dcinst" Source="dcinst\dcinst.vcproj" Description="Converting project file 'C:\Git\dcrypt\dcinst\dcinst.vcproj'.">
</Event><Event ErrorLevel="1" Project="dcinst" Source="dcinst\dcinst.vcproj" Description="VCWebServiceProxyGeneratorTool is no longer supported. The tool has been removed from your project settings.">
</Event><Event ErrorLevel="1" Project="dcinst" Source="dcinst\dcinst.vcproj" Description="VCConvertEngine could not convert attribute DependencyInformationFile = $(OutDir)obj\$(ProjectName)\mt.dep under Tool VCManifestTool.">
</Event><Event ErrorLevel="1" Project="dcinst" Source="dcinst\dcinst.vcproj" Description="VCConvertEngine could not convert attribute DependencyInformationFile = $(OutDir)obj\$(ProjectName)\mt.dep under Tool VCManifestTool.">
</Event><Event ErrorLevel="1" Project="dcinst" Source="dcinst\dcinst.vcproj" Description="VCConvertEngine could not convert attribute DependencyInformationFile = $(OutDir)obj\$(ProjectName)\mt.dep under Tool VCManifestTool.">
</Event><Event ErrorLevel="1" Project="dcinst" Source="dcinst\dcinst.vcproj" Description="VCConvertEngine could not convert attribute DependencyInformationFile = $(OutDir)obj\$(ProjectName)\mt.dep under Tool VCManifestTool.">
</Event><Event ErrorLevel="0" Project="dcinst" Source="dcinst\dcinst.vcproj" Description="Done converting to new project file 'C:\Git\dcrypt\dcinst\dcinst.vcxproj'.">
</Event><Event ErrorLevel="3" Project="dcinst" Source="dcinst\dcinst.vcproj" Description="Converted">
</Event><Event ErrorLevel="0" Project="boot_hook" Source="boot\boot_hook.vcproj" Description="Converting project file 'C:\Git\dcrypt\boot\boot_hook.vcproj'.">
</Event><Event ErrorLevel="1" Project="boot_hook" Source="boot\boot_hook.vcproj" Description="VCWebServiceProxyGeneratorTool is no longer supported. The tool has been removed from your project settings.">
</Event><Event ErrorLevel="1" Project="boot_hook" Source="boot\boot_hook.vcproj" Description="MSB8012: $(TargetExt) ('.exe') does not match the Linker's OutputFile property value 'C:\Git\dcrypt\boot\\bin\boot_hook.dll' ('.dll') in project configuration 'Release|Win32'. This may cause your project to build incorrectly. To correct this, please make sure that $(TargetExt) property value matches the value specified in %(Link.OutputFile).">
</Event><Event ErrorLevel="1" Project="boot_hook" Source="boot\boot_hook.vcproj" Description="MSB8012: $(TargetPath) ('C:\Git\dcrypt\\Release\boot\boot_hook.exe') does not match the Linker's OutputFile property value 'C:\Git\dcrypt\boot\\bin\boot_hook.dll' ('C:\Git\dcrypt\boot\\bin\boot_hook.dll') in project configuration 'Release|Win32'. This may cause your project to build incorrectly. To correct this, please make sure that $(TargetPath) property value matches the value specified in %(Link.OutputFile).">
</Event><Event ErrorLevel="0" Project="boot_hook" Source="boot\boot_hook.vcproj" Description="Done converting to new project file 'C:\Git\dcrypt\boot\boot_hook.vcxproj'.">
</Event><Event ErrorLevel="3" Project="boot_hook" Source="boot\boot_hook.vcproj" Description="Converted">
</Event><Event ErrorLevel="0" Project="boot_load" Source="boot\boot_load.vcproj" Description="Converting project file 'C:\Git\dcrypt\boot\boot_load.vcproj'.">
</Event><Event ErrorLevel="1" Project="boot_load" Source="boot\boot_load.vcproj" Description="VCWebServiceProxyGeneratorTool is no longer supported. The tool has been removed from your project settings.">
</Event><Event ErrorLevel="1" Project="boot_load" Source="boot\boot_load.vcproj" Description="MSB8012: $(TargetExt) ('.exe') does not match the Linker's OutputFile property value 'C:\Git\dcrypt\boot\\bin\boot_load.dll' ('.dll') in project configuration 'Release|Win32'. This may cause your project to build incorrectly. To correct this, please make sure that $(TargetExt) property value matches the value specified in %(Link.OutputFile).">
</Event><Event ErrorLevel="1" Project="boot_load" Source="boot\boot_load.vcproj" Description="MSB8012: $(TargetPath) ('C:\Git\dcrypt\\Release\boot\boot_load.exe') does not match the Linker's OutputFile property value 'C:\Git\dcrypt\boot\\bin\boot_load.dll' ('C:\Git\dcrypt\boot\\bin\boot_load.dll') in project configuration 'Release|Win32'. This may cause your project to build incorrectly. To correct this, please make sure that $(TargetPath) property value matches the value specified in %(Link.OutputFile).">
</Event><Event ErrorLevel="0" Project="boot_load" Source="boot\boot_load.vcproj" Description="Done converting to new project file 'C:\Git\dcrypt\boot\boot_load.vcxproj'.">
</Event><Event ErrorLevel="3" Project="boot_load" Source="boot\boot_load.vcproj" Description="Converted">
</Event><Event ErrorLevel="0" Project="pe2boot" Source="boot\pe2boot.vcproj" Description="Converting project file 'C:\Git\dcrypt\boot\pe2boot.vcproj'.">
</Event><Event ErrorLevel="1" Project="pe2boot" Source="boot\pe2boot.vcproj" Description="VCWebServiceProxyGeneratorTool is no longer supported. The tool has been removed from your project settings.">
</Event><Event ErrorLevel="1" Project="pe2boot" Source="boot\pe2boot.vcproj" Description="VCConvertEngine could not convert attribute DependencyInformationFile = $(OutDir)obj\$(ProjectName)\mt.dep under Tool VCManifestTool.">
</Event><Event ErrorLevel="1" Project="pe2boot" Source="boot\pe2boot.vcproj" Description="MSB8012: $(TargetPath) ('C:\Git\dcrypt\\Release\boot\pe2boot.exe') does not match the Linker's OutputFile property value 'C:\Git\dcrypt\boot\\bin\pe2boot.exe' ('C:\Git\dcrypt\boot\\bin\pe2boot.exe') in project configuration 'Release|Win32'. This may cause your project to build incorrectly. To correct this, please make sure that $(TargetPath) property value matches the value specified in %(Link.OutputFile).">
</Event><Event ErrorLevel="1" Project="pe2boot" Source="boot\pe2boot.vcproj" Description="MSB8012: $(TargetPath) ('C:\Git\dcrypt\\Debug\boot\pe2boot.exe') does not match the Linker's OutputFile property value 'C:\Git\dcrypt\boot\\bin\pe2boot.exe' ('C:\Git\dcrypt\boot\\bin\pe2boot.exe') in project configuration 'Debug|Win32'. This may cause your project to build incorrectly. To correct this, please make sure that $(TargetPath) property value matches the value specified in %(Link.OutputFile).">
</Event><Event ErrorLevel="0" Project="pe2boot" Source="boot\pe2boot.vcproj" Description="Done converting to new project file 'C:\Git\dcrypt\boot\pe2boot.vcxproj'.">
</Event><Event ErrorLevel="3" Project="pe2boot" Source="boot\pe2boot.vcproj" Description="Converted">
</Event><Event ErrorLevel="0" Project="boot_stage0" Source="boot\boot_stage0.vcproj" Description="Converting project file 'C:\Git\dcrypt\boot\boot_stage0.vcproj'.">
</Event><Event ErrorLevel="0" Project="boot_stage0" Source="boot\boot_stage0.vcproj" Description="Done converting to new project file 'C:\Git\dcrypt\boot\boot_stage0.vcxproj'.">
</Event><Event ErrorLevel="3" Project="boot_stage0" Source="boot\boot_stage0.vcproj" Description="Converted">
</Event><Event ErrorLevel="0" Project="crypto_test_1" Source="unit_tests\crypto_test_1.vcproj" Description="Converting project file 'C:\Git\dcrypt\unit_tests\crypto_test_1.vcproj'.">
</Event><Event ErrorLevel="1" Project="crypto_test_1" Source="unit_tests\crypto_test_1.vcproj" Description="VCWebServiceProxyGeneratorTool is no longer supported. The tool has been removed from your project settings.">
</Event><Event ErrorLevel="1" Project="crypto_test_1" Source="unit_tests\crypto_test_1.vcproj" Description="VCConvertEngine could not convert attribute DependencyInformationFile = $(OutDir)obj\$(ProjectName)\mt.dep under Tool VCManifestTool.">
</Event><Event ErrorLevel="1" Project="crypto_test_1" Source="unit_tests\crypto_test_1.vcproj" Description="VCConvertEngine could not convert attribute DependencyInformationFile = $(OutDir)obj\$(ProjectName)\mt.dep under Tool VCManifestTool.">
</Event><Event ErrorLevel="0" Project="crypto_test_1" Source="unit_tests\crypto_test_1.vcproj" Description="Done converting to new project file 'C:\Git\dcrypt\unit_tests\crypto_test_1.vcxproj'.">
</Event><Event ErrorLevel="3" Project="crypto_test_1" Source="unit_tests\crypto_test_1.vcproj" Description="Converted">
</Event><Event ErrorLevel="0" Project="crypto_test_2" Source="unit_tests\crypto_test_2.vcproj" Description="Converting project file 'C:\Git\dcrypt\unit_tests\crypto_test_2.vcproj'.">
</Event><Event ErrorLevel="1" Project="crypto_test_2" Source="unit_tests\crypto_test_2.vcproj" Description="VCWebServiceProxyGeneratorTool is no longer supported. The tool has been removed from your project settings.">
</Event><Event ErrorLevel="1" Project="crypto_test_2" Source="unit_tests\crypto_test_2.vcproj" Description="VCConvertEngine could not convert attribute DependencyInformationFile = $(OutDir)obj\$(ProjectName)\mt.dep under Tool VCManifestTool.">
</Event><Event ErrorLevel="1" Project="crypto_test_2" Source="unit_tests\crypto_test_2.vcproj" Description="VCConvertEngine could not convert attribute DependencyInformationFile = $(OutDir)obj\$(ProjectName)\mt.dep under Tool VCManifestTool.">
</Event><Event ErrorLevel="0" Project="crypto_test_2" Source="unit_tests\crypto_test_2.vcproj" Description="Done converting to new project file 'C:\Git\dcrypt\unit_tests\crypto_test_2.vcxproj'.">
</Event><Event ErrorLevel="3" Project="crypto_test_2" Source="unit_tests\crypto_test_2.vcproj" Description="Converted">
</Event><Event ErrorLevel="0" Project="boot_hook_small" Source="boot\boot_hook_small.vcproj" Description="Converting project file 'C:\Git\dcrypt\boot\boot_hook_small.vcproj'.">
</Event><Event ErrorLevel="1" Project="boot_hook_small" Source="boot\boot_hook_small.vcproj" Description="VCWebServiceProxyGeneratorTool is no longer supported. The tool has been removed from your project settings.">
</Event><Event ErrorLevel="1" Project="boot_hook_small" Source="boot\boot_hook_small.vcproj" Description="MSB8012: $(TargetExt) ('.exe') does not match the Linker's OutputFile property value 'C:\Git\dcrypt\boot\\bin\boot_hook_small.dll' ('.dll') in project configuration 'Release|Win32'. This may cause your project to build incorrectly. To correct this, please make sure that $(TargetExt) property value matches the value specified in %(Link.OutputFile).">
</Event><Event ErrorLevel="1" Project="boot_hook_small" Source="boot\boot_hook_small.vcproj" Description="MSB8012: $(TargetPath) ('C:\Git\dcrypt\\Release\boot\boot_hook_small.exe') does not match the Linker's OutputFile property value 'C:\Git\dcrypt\boot\\bin\boot_hook_small.dll' ('C:\Git\dcrypt\boot\\bin\boot_hook_small.dll') in project configuration 'Release|Win32'. This may cause your project to build incorrectly. To correct this, please make sure that $(TargetPath) property value matches the value specified in %(Link.OutputFile).">
</Event><Event ErrorLevel="0" Project="boot_hook_small" Source="boot\boot_hook_small.vcproj" Description="Done converting to new project file 'C:\Git\dcrypt\boot\boot_hook_small.vcxproj'.">
</Event><Event ErrorLevel="3" Project="boot_hook_small" Source="boot\boot_hook_small.vcproj" Description="Converted">
</Event><Event ErrorLevel="0" Project="" Source="dcrypt.sln" Description="Solution converted successfully">
</Event><Event ErrorLevel="3" Project="" Source="dcrypt.sln" Description="Converted">
</Event></UpgradeLog>